usbreq/__init__.py
usbreq-0.2.1.dist-info/LICENSE
usbreq-0.2.1.dist-info/METADATA
usbreq-0.2.1.dist-info/WHEEL
usbreq-0.2.1.dist-info/top_level.txt
usbreq-0.2.1.dist-info/RECORD
