Metadata-Version: 2.1
Name: usbreq
Version: 0.2.1
Summary: A USB library for humans
Home-page: https://github.com/Qyriad/python-usbreq
Author: Mikaela Szekely
Author-email: mikaela.szekely@qyriad.me
License: MIT
Platform: any
Classifier: Programming Language :: Python
Classifier: Development Status :: 3 - Alpha
Classifier: Natural Language :: English
Classifier: License :: OSI Approved :: MIT License
Classifier: Environment :: Console
Classifier: Intended Audience :: Developers
Classifier: Operating System :: OS Independent
Classifier: Topic :: Scientific/Engineering
Classifier: Topic :: Software Development
Classifier: Topic :: System :: Hardware :: Universal Serial Bus (USB)
Requires-Python: >= 3.9
License-File: LICENSE
Requires-Dist: pyusb
Requires-Dist: inflection
Provides-Extra: docs
Requires-Dist: sphinx-rtd-theme ; extra == 'docs'
